mangi_script/__init__.py
mangi_script/mangi_script.py
mangi_script-0.0.1.dist-info/LICENSE
mangi_script-0.0.1.dist-info/METADATA
mangi_script-0.0.1.dist-info/WHEEL
mangi_script-0.0.1.dist-info/top_level.txt
mangi_script-0.0.1.dist-info/RECORD
