Metadata-Version: 2.1
Name: mangi-script
Version: 0.0.1
Summary: Mangi Script
Home-page: https://github.com/pypa/sampleproject
Author: Gaurav
Author-email: author@example.com
License: UNKNOWN
Platform: UNKNOWN
Classifier: Programming Language :: Python :: 3
Classifier: License :: OSI Approved :: MIT License
Classifier: Operating System :: OS Independent
Requires-Python: >=3.6
